acmev2/__init__.py
acmev2/errors.py
acmev2/logging.py
acmev2/settings.py
acmev2/challenges/__init__.py
acmev2/challenges/base.py
acmev2/challenges/custom.py
acmev2/challenges/http.py
acmev2/handlers/__init__.py
acmev2/handlers/authorization.py
acmev2/handlers/base.py
acmev2/handlers/certificate.py
acmev2/handlers/challenge.py
acmev2/handlers/handler.py
acmev2/handlers/new_account.py
acmev2/handlers/new_nonce.py
acmev2/handlers/order.py
acmev2/messages/__init__.py
acmev2/messages/account.py
acmev2/messages/authz.py
acmev2/messages/base.py
acmev2/messages/certificate.py
acmev2/messages/challenge.py
acmev2/messages/nonce.py
acmev2/messages/order.py
acmev2/models/__init__.py
acmev2/models/account.py
acmev2/models/authorization.py
acmev2/models/base.py
acmev2/models/certificate.py
acmev2/models/challenge.py
acmev2/models/identifiers.py
acmev2/models/nonce.py
acmev2/models/order.py
acmev2/models/problem.py
acmev2/services/__init__.py
acmev2/services/services.py
acmev2/tests/__init__.py
acmev2/tests/conftest.py
acmev2/tests/helpers.py
acmev2/tests/test_base.py
acmev2/tests/test_invalid_account.py
acmev2/tests/test_invalid_content_type.py
acmev2/tests/test_invalid_url.py
acmev2/tests/test_resolve_state.py
acmev2/tests/test_services.py
acmev2/tests/challenges/test_auth_state_change.py
acmev2/tests/challenges/test_http.py
acmev2/tests/clients/test_caddy.py
acmev2/tests/clients/test_certbot.py
acmev2/tests/clients/test_getssl.py
acmev2/tests/handlers/__init__.py
acmev2/tests/handlers/test_authorization.py
acmev2/tests/handlers/test_cert.py
acmev2/tests/handlers/test_challenge.py
acmev2/tests/handlers/test_finalize.py
acmev2/tests/handlers/test_newaccount.py
acmev2/tests/handlers/test_neworder.py
acmev2/tests/handlers/test_nonce.py
acmev2/tests/handlers/test_order.py
acmev2/tests/xprocess/acme_server.py
acmev2/tests/xprocess/http_redirector.py
acmev2/tests/xprocess/https_server.py
acmev2-0.1.1.dist-info/METADATA
acmev2-0.1.1.dist-info/WHEEL
acmev2-0.1.1.dist-info/top_level.txt
acmev2-0.1.1.dist-info/RECORD
