Metadata-Version: 2.4
Name: acmev2
Version: 0.1.1
Summary: ACME v2 Protocol Implementation (limited)
License: Apache-2.0
Requires-Python: >=3.11
Requires-Dist: inject>=5.2.1
Requires-Dist: josepy>=1.14.0
Requires-Dist: parse>=1.20.2
Requires-Dist: pydantic-settings>=2.5.2
Requires-Dist: pydantic>=2.9.1
Requires-Dist: requests>=2.32.3
